lunarcrush/__init__.py
lunarcrush/lunarcrush.py
LunarCrushAPI-1.0.2.dist-info/LICENSE
LunarCrushAPI-1.0.2.dist-info/METADATA
LunarCrushAPI-1.0.2.dist-info/WHEEL
LunarCrushAPI-1.0.2.dist-info/top_level.txt
LunarCrushAPI-1.0.2.dist-info/RECORD
