Metadata-Version: 2.1
Name: LunarCrushAPI
Version: 1.0.2
Summary: Unofficial LunarCrush API v2 Wrapper for Python.
Home-page: https://github.com/saizk/LunarCrushAPI
Author: saizk
Author-email: saizk <sergioaizcorbe@hotmail.com>
License: MIT License        
Project-URL: Homepage, https://github.com/saizk/LunarCrushAPI
Project-URL: Bug Tracker, https://github.com/saizk/LunarCrushAPI/issues
Classifier: Programming Language :: Python :: 3
Classifier: Programming Language :: Python :: 3.6
Classifier: Programming Language :: Python :: 3.7
Classifier: Programming Language :: Python :: 3.8
Classifier: Programming Language :: Python :: 3.9
Classifier: Programming Language :: Python :: 3.10
Classifier: License :: OSI Approved :: MIT License
Classifier: Operating System :: OS Independent
Requires-Python: >=3.6
License-File: LICENSE
Requires-Dist: requests
